radviz_plotly/RadViz2D.py
radviz_plotly/RadViz3D.py
radviz_plotly/RadViz3DH.py
radviz_plotly/RadViz3DSort.py
radviz_plotly/_2D_submodules/RadViz_mapping.py
radviz_plotly/_2D_submodules/_2Dscatterplot_plotly.py
radviz_plotly/_2D_submodules/__init__.py
radviz_plotly/_2D_submodules/get_anchors_matrix.py
radviz_plotly/_2D_submodules/normalizing.py
radviz_plotly/_2D_submodules/plotly_2Dframe.py
radviz_plotly/_2D_submodules/points_oncircle.py
radviz_plotly/_3D_submodules/RadViz_mapping.py
radviz_plotly/_3D_submodules/_3Dscatterplot_plotly.py
radviz_plotly/_3D_submodules/__init__.py
radviz_plotly/_3D_submodules/get_anchors_matrix.py
radviz_plotly/_3D_submodules/normalizing.py
radviz_plotly/_3D_submodules/plotly_3Dframe.py
radviz_plotly/_3D_submodules/points_onsphere.py
radviz_plotly/_3D_submodules/sorting_utils.py
radviz_plotly/__init__.py
radviz_plotly/main.py
radviz_plotly-0.2.0.dist-info/METADATA
radviz_plotly-0.2.0.dist-info/WHEEL
radviz_plotly-0.2.0.dist-info/licenses/LICENSE
radviz_plotly-0.2.0.dist-info/RECORD
