Metadata-Version: 2.4
Name: radviz-plotly
Version: 0.2.0
Summary: A Python package for 2D and 3D Radial Visualization using Plotly with attribute sorting
License: MIT
License-File: LICENSE
Keywords: visualization,radviz,plotly,data-science,3d-visualization
Author: elewah
Author-email: abdelrahman.elewah@gmail.com
Requires-Python: >=3.8,<4.0
Classifier: Intended Audience :: Science/Research
Classifier: License :: OSI Approved :: MIT License
Classifier: Operating System :: OS Independent
Classifier: Programming Language :: Python :: 3
Classifier: Programming Language :: Python :: 3.8
Classifier: Programming Language :: Python :: 3.9
Classifier: Programming Language :: Python :: 3.10
Classifier: Programming Language :: Python :: 3.11
Classifier: Programming Language :: Python :: 3.12
Classifier: Programming Language :: Python :: 3.13
Classifier: Programming Language :: Python :: 3.14
Classifier: Topic :: Scientific/Engineering :: Visualization
Provides-Extra: sorting
Requires-Dist: numpy (>=1.18.0)
Requires-Dist: pandas (>=1.0.0)
Requires-Dist: plotly (>=4.0.0)
Requires-Dist: scikit-learn (>=0.24.0) ; extra == "sorting"
Requires-Dist: transformations (>=2020.1.1) ; extra == "sorting"
Project-URL: Homepage, https://github.com/elewah/RadViz-Plotly
Project-URL: Repository, https://github.com/elewah/RadViz-Plotly.git
